Products.MailHost-6.0-py3.13-nspkg.pth
Products/MailHost/MailHost.py
Products/MailHost/SendMailTag.py
Products/MailHost/__init__.py
Products/MailHost/configure.zcml
Products/MailHost/decorator.py
Products/MailHost/exportimport.py
Products/MailHost/exportimport.zcml
Products/MailHost/interfaces.py
Products/MailHost/mailer.py
Products/MailHost/dtml/addMailHost_form.dtml
Products/MailHost/dtml/manageMailHost.dtml
Products/MailHost/tests/__init__.py
Products/MailHost/tests/dummy.py
Products/MailHost/tests/testMailHost.py
Products/MailHost/tests/test_SendMailTag.py
Products/MailHost/tests/test_exportimport.py
Products/MailHost/www/MailHost_icon.gif
Products.MailHost-6.0.dist-info/LICENSE.txt
Products.MailHost-6.0.dist-info/METADATA
Products.MailHost-6.0.dist-info/WHEEL
Products.MailHost-6.0.dist-info/namespace_packages.txt
Products.MailHost-6.0.dist-info/top_level.txt
Products.MailHost-6.0.dist-info/RECORD
