Metadata-Version: 2.1
Name: Products.MailHost
Version: 6.0
Summary: zope.sendmail integration for Zope.
Home-page: https://github.com/zopefoundation/Products.MailHost
Author: Zope Foundation and Contributors
Author-email: zope-dev@zope.dev
License: ZPL-2.1
Project-URL: Issue Tracker, https://github.com/zopefoundation/Products.MailHost/issues
Project-URL: Sources, https://github.com/zopefoundation/Products.MailHost
Classifier: Development Status :: 6 - Mature
Classifier: Environment :: Web Environment
Classifier: Framework :: Zope
Classifier: Framework :: Zope :: 5
Classifier: License :: OSI Approved :: Zope Public License
Classifier: Operating System :: OS Independent
Classifier: Programming Language :: Python
Classifier: Programming Language :: Python :: 3
Classifier: Programming Language :: Python :: 3.9
Classifier: Programming Language :: Python :: 3.10
Classifier: Programming Language :: Python :: 3.11
Classifier: Programming Language :: Python :: 3.12
Classifier: Programming Language :: Python :: 3.13
Classifier: Programming Language :: Python :: Implementation :: CPython
Classifier: Topic :: Communications :: Email
Requires-Python: >=3.9
License-File: LICENSE.txt
Requires-Dist: setuptools
Requires-Dist: AccessControl
Requires-Dist: Acquisition
Requires-Dist: DateTime
Requires-Dist: DocumentTemplate
Requires-Dist: ExtensionClass>=4.1a1
Requires-Dist: Persistence
Requires-Dist: Zope>=4.0b4
Requires-Dist: zope.deferredimport
Requires-Dist: zope.interface
Requires-Dist: zope.sendmail>=6.2
Provides-Extra: genericsetup
Requires-Dist: Products.GenericSetup>=2.0b1; extra == "genericsetup"
